{
    "comfyui": "548457bac47bb6c0ce233a9f5abb3467582d710d",
    "git_custom_nodes": {
        "https://github.com/Jordach/comfy-plasma": {
            "hash": "c63555fec40a7dddb36c99aa603e817abab3abdb",
            "disabled": false
        },
        "https://github.com/M1kep/ComfyLiterals": {
            "hash": "bdddb08ca82d90d75d97b1d437a652e0284a32ac",
            "disabled": false
        },
        "https://github.com/theUpsider/ComfyUI-Logic": {
            "hash": "42d4f3df45fb7f0dd6e2201a14c07d4dd09f235d",
            "disabled": false
        },
        "https://github.com/ltdrdata/ComfyUI-Manager": {
            "hash": "908a1009d25a85bae7caeba534046153ef04f97d",
            "disabled": false
        },
        "https://codeberg.org/Gourieff/comfyui-reactor-node.git": {
            "hash": "976a8c51bab55fe5443392566ab4e6a9315eed6a",
            "disabled": false
        },
        "https://github.com/Suzie1/ComfyUI_Comfyroll_CustomNodes": {
            "hash": "d78b780ae43fcf8c6b7c6505e6ffb4584281ceca",
            "disabled": false
        }
    },
    "cnr_custom_nodes": {
        "cg-use-everywhere": "5.0.9",
        "comfyui-custom-scripts": "1.2.3",
        "comfyui-easy-use": "1.2.8",
        "comfyui-inpaint-nodes": "1.0.4",
        "comfyui-kjnodes": "1.0.8",
        "comfyui_controlnet_aux": "1.0.7",
        "comfyui_instantid": "1.0.0",
        "was-node-suite-comfyui": "1.0.2"
    },
    "file_custom_nodes": [
        {
            "filename": "websocket_image_save.py",
            "disabled": false
        }
    ],
    "pips": {
        
    }
}
